spalor/__init__.py
spalor/algorithms/__init__.py
spalor/algorithms/cx_algorithms.py
spalor/algorithms/lasso_algorithms.py
spalor/algorithms/mc_algorithms.py
spalor/algorithms/rpca_algorithms.py
spalor/datasets/__init__.py
spalor/datasets/collaborative_filtering.py
spalor/datasets/fish_videos.py
spalor/datasets/stt.py
spalor/datasets/synthetic_test_data.py
spalor/matrix_tools/__init__.py
spalor/matrix_tools/factorization_util.py
spalor/matrix_tools/leverage_score.py
spalor/models/__init__.py
spalor/models/cur.py
spalor/models/cx.py
spalor/models/mc.py
spalor/models/reweighted_lasso.py
spalor/models/robust_pca.py
spalor/regularization/__init__.py
spalor/regularization/regularizers.py
spalor/regularization/thresholding.py
tests/__init__.py
tests/test_cur.py
tests/test_cx.py
tests/test_data_loaders.py
tests/test_mc.py
tests/test_regularizers.py
tests/test_reweighted_lasso.py
tests/test_robust_pca.py
tests/test_sparse_pca.py
SpaLoR-0.2.dist-info/LICENSE
SpaLoR-0.2.dist-info/METADATA
SpaLoR-0.2.dist-info/WHEEL
SpaLoR-0.2.dist-info/top_level.txt
SpaLoR-0.2.dist-info/RECORD
